synth/ckt.v

module mux(i1,i0,s,y);
    input i1,i0,s;
    output y;

    assign y=s?i1:i0;
endmodule

module ckt(a,b,c,y);
    input a,b,c;
    output y;
    wire w1,w2;
    mux m1(b,1'b1,c,w1);
    mux m2(1'b0,1'b1,b,w2);
    mux m3(w2,w1,a,y);
endmodule

synth/tb_ckt.v
module tb;
     reg a,b,c;
     wire y;

     ckt c1(a,b,c,y);

     initial begin
      $dumpfile("ckt.vcd");
	   $dumpvars(0,tb);
      a=0;b=0;c=0;
      #10;
      $display("%b %b %b %b",a,b,c,y);
      a=0;b=0;c=1;
      #10;
      $display("%b %b %b %b",a,b,c,y);
      a=0;b=1;c=0;
      #10;
      $display("%b %b %b %b",a,b,c,y);
      a=0;b=1;c=1;
      #10;
      $display("%b %b %b %b",a,b,c,y);
      a=1;b=0;c=0;
      #10;
      $display("%b %b %b %b",a,b,c,y);
      a=1;b=0;c=1;
      #10;
      $display("%b %b %b %b",a,b,c,y);
      a=1;b=1;c=0;
      #10;
      $display("%b %b %b %b",a,b,c,y);
      a=1;b=1;c=1;
      #10;
      $display("%b %b %b %b",a,b,c,y);
      $finish;
     end
endmodule

synth/ckt.vcd
$date
	Tue Jul 20 08:38:32 2021
$end
$version
	Icarus Verilog
$end
$timescale
	1s
$end
$scope module tb $end
$var wire 1 ! y $end
$var reg 1 " a $end
$var reg 1 # b $end
$var reg 1 $ c $end
$scope module c1 $end
$var wire 1 " a $end
$var wire 1 # b $end
$var wire 1 $ c $end
$var wire 1 ! y $end
$var wire 1 % w2 $end
$var wire 1 & w1 $end
$scope module m1 $end
$var wire 1 ' i0 $end
$var wire 1 # i1 $end
$var wire 1 $ s $end
$var wire 1 & y $end
$upscope $end
$scope module m2 $end
$var wire 1 ( i0 $end
$var wire 1 ) i1 $end
$var wire 1 # s $end
$var wire 1 % y $end
$upscope $end
$scope module m3 $end
$var wire 1 & i0 $end
$var wire 1 % i1 $end
$var wire 1 " s $end
$var wire 1 ! y $end
$upscope $end
$upscope $end
$upscope $end
$enddefinitions $end
#0
$dumpvars
0)
1(
1'
1&
1%
0$
0#
0"
1!
$end
#10
0!
0&
1$
#20
1!
1&
0%
0$
1#
#30
1$
#40
1%
1!
0$
0#
1"
#50
0&
1$
#60
0!
1&
0%
0$
1#
#70
1$
